kitescraper/__init__.py
kitescraper/login.py
kitescraper/scrape.py
kitescraper-0.0.3.dist-info/METADATA
kitescraper-0.0.3.dist-info/WHEEL
kitescraper-0.0.3.dist-info/top_level.txt
kitescraper-0.0.3.dist-info/RECORD
